<?xml version="1.0" encoding="UTF-8"?><apiPackage id="com.rosettastone.library.taskmanager.events"><apiName>com.rosettastone.library.taskmanager.events</apiName><apiDetail/><apiClassifier id="com.rosettastone.library.taskmanager.events:TaskEvent"><apiName>TaskEvent</apiName><shortdesc>
	 Dispatched by a Task to indicated a change in state.</shortdesc><prolog><asMetadata/></prolog><apiClassifierDetail><apiClassifierDef><apiAccess value="public"/><apiStatic/><apiBaseClassifier>flash.events:Event</apiBaseClassifier></apiClassifierDef><apiDesc>
	 Dispatched by a Task to indicated a change in state.
	 </apiDesc></apiClassifierDetail><apiConstructor id="com.rosettastone.library.taskmanager.events:TaskEvent:TaskEvent"><apiName>TaskEvent</apiName><shortdesc/><prolog/><apiConstructorDetail><apiConstructorDef><apiAccess value="public"/><apiParam><apiItemName>type</apiItemName><apiType value="String"/></apiParam><apiParam><apiItemName>message</apiItemName><apiType value="String"/><apiData/></apiParam><apiParam><apiItemName>data</apiItemName><apiType value="any"/><apiData>null</apiData></apiParam></apiConstructorDef></apiConstructorDetail></apiConstructor><apiOperation id="com.rosettastone.library.taskmanager.events:TaskEvent:clone"><apiName>clone</apiName><shortdesc>
		 </shortdesc><prolog/><apiOperationDetail><apiOperationDef><apiAccess value="public"/><apiIsOverride/><apiReturn><apiType value="flash.events:Event"/></apiReturn></apiOperationDef><apiDesc>
		 </apiDesc></apiOperationDetail><apiInheritDoc/></apiOperation><apiValue id="com.rosettastone.library.taskmanager.events:TaskEvent:COMPLETE"><apiName>COMPLETE</apiName><shortdesc/><prolog/><apiValueDetail><apiValueDef><apiAccess value="public"/><apiStatic/><apiData>taskEventComplete</apiData><apiType value="String"/></apiValueDef></apiValueDetail></apiValue><apiValue id="com.rosettastone.library.taskmanager.events:TaskEvent:ERROR"><apiName>ERROR</apiName><shortdesc/><prolog/><apiValueDetail><apiValueDef><apiAccess value="public"/><apiStatic/><apiData>taskEventError</apiData><apiType value="String"/></apiValueDef></apiValueDetail></apiValue><apiValue id="com.rosettastone.library.taskmanager.events:TaskEvent:FINAL"><apiName>FINAL</apiName><shortdesc/><prolog/><apiValueDetail><apiValueDef><apiAccess value="public"/><apiStatic/><apiData>taskEventFinal</apiData><apiType value="String"/></apiValueDef></apiValueDetail></apiValue><apiValue id="com.rosettastone.library.taskmanager.events:TaskEvent:INTERRUPTED"><apiName>INTERRUPTED</apiName><shortdesc/><prolog/><apiValueDetail><apiValueDef><apiAccess value="public"/><apiStatic/><apiData>taskEventInterrupted</apiData><apiType value="String"/></apiValueDef></apiValueDetail></apiValue><apiValue id="com.rosettastone.library.taskmanager.events:TaskEvent:STARTED"><apiName>STARTED</apiName><shortdesc/><prolog/><apiValueDetail><apiValueDef><apiAccess value="public"/><apiStatic/><apiData>taskEventStarted</apiData><apiType value="String"/></apiValueDef></apiValueDetail></apiValue><apiValue id="com.rosettastone.library.taskmanager.events:TaskEvent:data:get"><apiName>data</apiName><shortdesc>
		 Optional data object related to the Task dispatching this event.</shortdesc><prolog/><apiValueDetail><apiValueDef><apiProperty/><apiAccess value="public"/><apiDynamic/><apiValueAccess value="readwrite"/><apiType value="any"/></apiValueDef><apiDesc>
		 Optional data object related to the Task dispatching this event.
		 If the event is an error event this object may also contain more information about the error.
		 </apiDesc></apiValueDetail></apiValue><apiValue id="com.rosettastone.library.taskmanager.events:TaskEvent:message:get"><apiName>message</apiName><shortdesc>
		 Optional human-readable message.</shortdesc><prolog/><apiValueDetail><apiValueDef><apiProperty/><apiAccess value="public"/><apiDynamic/><apiValueAccess value="readwrite"/><apiType value="String"/></apiValueDef><apiDesc>
		 Optional human-readable message.
		 </apiDesc></apiValueDetail></apiValue></apiClassifier><apiClassifier id="com.rosettastone.library.taskmanager.events:TaskManagerEvent"><apiName>TaskManagerEvent</apiName><shortdesc>
	 Dispatched by TaskManager to indicate a change in state.</shortdesc><prolog><asMetadata/></prolog><apiClassifierDetail><apiClassifierDef><apiAccess value="public"/><apiStatic/><apiBaseClassifier>flash.events:Event</apiBaseClassifier></apiClassifierDef><apiDesc>
	 Dispatched by TaskManager to indicate a change in state.
	 </apiDesc></apiClassifierDetail><apiConstructor id="com.rosettastone.library.taskmanager.events:TaskManagerEvent:TaskManagerEvent"><apiName>TaskManagerEvent</apiName><shortdesc>
		 </shortdesc><prolog/><apiConstructorDetail><apiConstructorDef><apiAccess value="public"/><apiParam><apiItemName>type</apiItemName><apiType value="String"/><apiDesc>Event type
		 </apiDesc></apiParam><apiParam><apiItemName>task</apiItemName><apiOperationClassifier>com.rosettastone.library.taskmanager:ITask</apiOperationClassifier><apiData>null</apiData><apiDesc>Errored task (if event type is ERROR)
		 </apiDesc></apiParam><apiParam><apiItemName>message</apiItemName><apiType value="String"/><apiData>null</apiData><apiDesc>Optional message
		 </apiDesc></apiParam></apiConstructorDef><apiDesc>
		 </apiDesc></apiConstructorDetail></apiConstructor><apiOperation id="com.rosettastone.library.taskmanager.events:TaskManagerEvent:clone"><apiName>clone</apiName><shortdesc>
		 </shortdesc><prolog/><apiOperationDetail><apiOperationDef><apiAccess value="public"/><apiIsOverride/><apiReturn><apiType value="flash.events:Event"/></apiReturn></apiOperationDef><apiDesc>
		 </apiDesc></apiOperationDetail><apiInheritDoc/></apiOperation><apiValue id="com.rosettastone.library.taskmanager.events:TaskManagerEvent:COMPLETE"><apiName>COMPLETE</apiName><shortdesc/><prolog/><apiValueDetail><apiValueDef><apiAccess value="public"/><apiStatic/><apiData>taskManagerEventComplete</apiData><apiType value="String"/></apiValueDef></apiValueDetail></apiValue><apiValue id="com.rosettastone.library.taskmanager.events:TaskManagerEvent:ERROR"><apiName>ERROR</apiName><shortdesc/><prolog/><apiValueDetail><apiValueDef><apiAccess value="public"/><apiStatic/><apiData>taskManagerEventError</apiData><apiType value="String"/></apiValueDef></apiValueDetail></apiValue><apiValue id="com.rosettastone.library.taskmanager.events:TaskManagerEvent:INTERRUPTED"><apiName>INTERRUPTED</apiName><shortdesc/><prolog/><apiValueDetail><apiValueDef><apiAccess value="public"/><apiStatic/><apiData>taskManagerEventInterrupted</apiData><apiType value="String"/></apiValueDef></apiValueDetail></apiValue><apiValue id="com.rosettastone.library.taskmanager.events:TaskManagerEvent:message:get"><apiName>message</apiName><shortdesc>
		 Optional human-readable message.</shortdesc><prolog/><apiValueDetail><apiValueDef><apiProperty/><apiAccess value="public"/><apiDynamic/><apiValueAccess value="read"/><apiType value="String"/></apiValueDef><apiDesc>
		 Optional human-readable message.
		 </apiDesc></apiValueDetail></apiValue><apiValue id="com.rosettastone.library.taskmanager.events:TaskManagerEvent:task:get"><apiName>task</apiName><shortdesc>
		 Task associated with error (in the event of an error).</shortdesc><prolog/><apiValueDetail><apiValueDef><apiProperty/><apiAccess value="public"/><apiDynamic/><apiValueAccess value="read"/><apiValueClassifier>com.rosettastone.library.taskmanager:ITask</apiValueClassifier></apiValueDef><apiDesc>
		 Task associated with error (in the event of an error).
		 </apiDesc></apiValueDetail></apiValue></apiClassifier></apiPackage>